find_lunch_in_garda.py
bearnaise_bot-0.1.4.dist-info/METADATA
bearnaise_bot-0.1.4.dist-info/WHEEL
bearnaise_bot-0.1.4.dist-info/entry_points.txt
bearnaise_bot-0.1.4.dist-info/top_level.txt
bearnaise_bot-0.1.4.dist-info/RECORD
