Metadata-Version: 2.1
Name: bearnaise-bot
Version: 0.1.4
Summary: Helps you fins a place in Gårda to have lunch.
Home-page: UNKNOWN
Author: Helena Strandberg
Author-email: helena.sisko.strandberg@gmail.com
License: UNKNOWN
Platform: UNKNOWN
Classifier: Development Status :: 3 - Alpha
Classifier: Programming Language :: Python :: 3.6
Classifier: Programming Language :: Python :: 3.7
Requires-Python: >=3.6
Requires-Dist: Click
Requires-Dist: requests-html
Requires-Dist: fuzzywuzzy
Requires-Dist: python-Levenshtein
